pyHoneygain/__init__.py
pyHoneygain/endpoints.py
pyHoneygain/exceptions.py
pyHoneygain/hg.py
pyHoneygain-0.3.9.dist-info/LICENSE
pyHoneygain-0.3.9.dist-info/METADATA
pyHoneygain-0.3.9.dist-info/WHEEL
pyHoneygain-0.3.9.dist-info/top_level.txt
pyHoneygain-0.3.9.dist-info/RECORD
