Metadata-Version: 2.1
Name: pyHoneygain
Version: 0.3.9
Summary: UNOFFICIAL Python bindings for Honeygain Dashboard API
Home-page: https://github.com/coder-amogh/pyHoneygain
Author: coder-amogh (Amogh Datar)
License: UNKNOWN
Project-URL: Bug Tracker, https://github.com/coder-amogh/pyHoneygain/issues
Keywords: python,honeygain,hg,passive income,honeygain api,honeygain dashboard,python honeygain
Platform: UNKNOWN
Classifier: Development Status :: 5 - Production/Stable
Classifier: Intended Audience :: Developers
Classifier: Programming Language :: Python :: 3
Classifier: Operating System :: OS Independent
Requires-Dist: requests
Requires-Dist: pySocks
